merlin_python_utils/__init__.py
merlin_python_utils/publisher.py
merlin_python_utils/test_publisher.py
merlin_python_utils/util.py
merlin_utils/__init__.py
merlin_utils/constants.py
merlin_utils/datastore.py
merlin_utils/model.py
merlin_utils/publisher.py
merlin_utils/schema.py
merlin_utils/spanner_client.py
merlin_utils/test_publisher.py
merlin_utils/util.py
merlin_utils-0.0.25.dist-info/METADATA
merlin_utils-0.0.25.dist-info/RECORD
merlin_utils-0.0.25.dist-info/WHEEL
merlin_utils-0.0.25.dist-info/top_level.txt
