Metadata-Version: 2.1
Name: merlin-utils
Version: 0.0.25
Summary: Merlin utils
Home-page: https://http//github.com/merlinapp/merlin_python_utils
Author: Merlin Jobs inc.
Author-email: oficina@merlinjobs.com
License: UNKNOWN
Platform: UNKNOWN
Classifier: Programming Language :: Python :: 3
Classifier: License :: OSI Approved :: MIT License
Classifier: Operating System :: OS Independent
Requires-Dist: Flask (==1.0.2)
Requires-Dist: google-api-python-client (==1.7.3)
Requires-Dist: google-auth (==1.5.0)
Requires-Dist: requests (==2.18.4)
Requires-Dist: oauth2client (==4.1.2)
Requires-Dist: Flask-api (==1.0.0)
Requires-Dist: google-cloud-datastore (==1.7.0)
Requires-Dist: google-cloud-pubsub (==0.37.0)
Requires-Dist: google-cloud-spanner (==1.6.0)
Requires-Dist: marshmallow (==2.15.4)
